MANIFEST.in
README.md
libest.py
setup.py
libest.egg-info/PKG-INFO
libest.egg-info/SOURCES.txt
libest.egg-info/dependency_links.txt
libest.egg-info/requires.txt
libest.egg-info/top_level.txt