Metadata-Version: 1.0
Name: libest
Version: 1.0.9
Summary: Library to communicate with Exercise Submission Tool (https://est.informatik.uni-erlangen.de)
Home-page: https://github.com/jneureuther/libest
Author: Julian Neureuther
Author-email: dev@jneureuther.de
License: CC BY-SA 4.0
Platform: UNKNOWN
